props/__init__.py
props-0.0.3.dist-info/METADATA
props-0.0.3.dist-info/RECORD
props-0.0.3.dist-info/WHEEL
props-0.0.3.dist-info/top_level.txt
