Metadata-Version: 1.1
Name: props
Version: 0.0.3
Summary: QuickCheck for Python
Home-page: https://www.github.com/zeckalpha/props
Author: Kyle Marek-Spartz
Author-email: kyle.marek.spartz@gmail.com
License: MIT
Platform: UNKNOWN
Classifier: Development Status :: 3 - Alpha
Classifier: Intended Audience :: Developers
Classifier: License :: OSI Approved :: MIT License
Classifier: Programming Language :: Python :: 2.7
